maznet/__init__.py
maznet/data.py
maznet/layers.py
maznet/loss.py
maznet/nn.py
maznet/optim.py
maznet/tensor.py
maznet/train.py
maznet-1.0.1.dist-info/LICENSE
maznet-1.0.1.dist-info/METADATA
maznet-1.0.1.dist-info/WHEEL
maznet-1.0.1.dist-info/top_level.txt
maznet-1.0.1.dist-info/RECORD
