Metadata-Version: 2.1
Name: maznet
Version: 1.0.1
Summary: A lightweight deep learning library
Home-page: https://github.com/Karnak123/maznet
Author: Sagnik Mazumder
Author-email: sagnikmazumdar37@gmail.com
License: MIT
Platform: UNKNOWN
Classifier: License :: OSI Approved :: MIT License
Classifier: Programming Language :: Python :: 3
Classifier: Programming Language :: Python :: 3.7
License-File: LICENSE
Requires-Dist: numpy
